backend_shim.py
uvicorn_tls-0.0.0.dist-info/METADATA
uvicorn_tls-0.0.0.dist-info/WHEEL
uvicorn_tls-0.0.0.dist-info/RECORD
