Metadata-Version: 2.1
Name: uvicorn-tls
Version: 0.0.0
Summary: ASGI TLS extension for Uvicorn 🔒
Author-email: Marcelo Trylesinski <marcelotryle@gmail.com>
License: MIT
